akamai_swissarmyknife/__init__.py
akamai_swissarmyknife/core.py
akamai_swissarmyknife-0.1.0.dist-info/licenses/LICENSE
akamai_swissarmyknife-0.1.0.dist-info/METADATA
akamai_swissarmyknife-0.1.0.dist-info/WHEEL
akamai_swissarmyknife-0.1.0.dist-info/top_level.txt
akamai_swissarmyknife-0.1.0.dist-info/RECORD
