Metadata-Version: 2.4
Name: akamai-swissarmyknife
Version: 0.1.0
Summary: Swiss Army Knife utilities for interacting with Akamai
Author: jakep
License: MIT
Requires-Python: >=3.7
License-File: LICENSE
Dynamic: license-file
